LICENSE.txt
README.md
setup.py
BPPU1/__init__.py
BPPU1/a.py
BPPU1.egg-info/PKG-INFO
BPPU1.egg-info/SOURCES.txt
BPPU1.egg-info/dependency_links.txt
BPPU1.egg-info/requires.txt
BPPU1.egg-info/top_level.txt